mogo/__init__.py
mogo/connection.py
mogo/cursor.py
mogo/decorators.py
mogo/field.py
mogo/helpers.py
mogo/model.py
mogo/py.typed
mogo-0.6.0.dist-info/LICENSE.txt
mogo-0.6.0.dist-info/METADATA
mogo-0.6.0.dist-info/WHEEL
mogo-0.6.0.dist-info/top_level.txt
mogo-0.6.0.dist-info/RECORD
