Metadata-Version: 2.1
Name: mogo
Version: 0.6.0
Summary: Simple PyMongo "schema-less" object wrapper
Home-page: http://github.com/joshmarshall/mogo/
Author: Josh Marshall
Author-email: catchjosh@gmail.com
License: http://www.apache.org/licenses/LICENSE-2.0
License-File: LICENSE.txt
Requires-Dist: pymongo >=4.1
